devrpa/__init__.py
devrpa/auth.py
devrpa/cache.py
devrpa/core.py
devrpa/flow.py
devrpa/logging.py
devrpa/policy.py
devrpa/resources.py
devrpa/selectors.py
devrpa/server.py
devrpa/state.py
devrpa/telemetry.py
devrpa/throttling.py
devrpa/workflow.py
devrpa/cli/__init__.py
devrpa/cli/interactive.py
devrpa/integrations/github.py
devrpa/integrations/slack.py
devrpa/steps/__init__.py
devrpa/steps/api.py
devrpa/steps/communication.py
devrpa/steps/data.py
devrpa/steps/db.py
devrpa/steps/file.py
devrpa/steps/files_extended.py
devrpa/steps/flow.py
devrpa/steps/system.py
devrpa/steps/web.py
devrpa-0.9.4.dist-info/licenses/LICENSE
devrpa-0.9.4.dist-info/METADATA
devrpa-0.9.4.dist-info/WHEEL
devrpa-0.9.4.dist-info/entry_points.txt
devrpa-0.9.4.dist-info/top_level.txt
devrpa-0.9.4.dist-info/RECORD
