Metadata-Version: 2.4
Name: devrpa
Version: 0.9.4
Summary: The Developer-First Automation Framework for Python.
Author-email: Prathamesh Fuke <prathamesh@example.com>
Maintainer-email: Prathamesh Fuke <prathamesh@example.com>
License: MIT License
Project-URL: Homepage, https://github.com/prathameshfuke/devrpa
Project-URL: Repository, https://github.com/prathameshfuke/devrpa.git
Project-URL: Issues, https://github.com/prathameshfuke/devrpa/issues
Classifier: Development Status :: 4 - Beta
Classifier: Intended Audience :: Developers
Classifier: Programming Language :: Python :: 3
Classifier: Programming Language :: Python :: 3.10
Classifier: Programming Language :: Python :: 3.11
Classifier: Programming Language :: Python :: 3.12
Classifier: Operating System :: OS Independent
Requires-Python: >=3.10
License-File: LICENSE
Requires-Dist: requests
Requires-Dist: playwright
Requires-Dist: httpx
Requires-Dist: sqlalchemy
Requires-Dist: aiosqlite
Requires-Dist: pydantic>=2.0
Requires-Dist: rich>=13.0
Requires-Dist: fastapi>=0.100.0
Requires-Dist: uvicorn>=0.23.0
Requires-Dist: websockets>=11.0
Requires-Dist: python-jose>=3.3.0
Requires-Dist: passlib[bcrypt]>=1.7.4
Requires-Dist: prometheus-client>=0.17.0
Requires-Dist: structlog>=23.1.0
Requires-Dist: textual>=0.40.0
Dynamic: license-file
